optima/__init__.py
optinet-0.1.7.dist-info/LICENSE
optinet-0.1.7.dist-info/METADATA
optinet-0.1.7.dist-info/WHEEL
optinet-0.1.7.dist-info/top_level.txt
optinet-0.1.7.dist-info/RECORD
