Metadata-Version: 2.2
Name: OptiNet
Version: 0.1.7
Summary: OptiNet is a Python library for optimizing traditional machine learning models.
Author: Vishwanath Akuthota ,Ganesh thota and Krishna Avula
License-File: LICENSE
Dynamic: author
Dynamic: description
Dynamic: description-content-type
Dynamic: summary
